{"route":"/docs/reference/layout/scale/","title":"Scale","description":"Documentation for the `scale` function.","part":null,"outline":[{"id":"summary","name":"概要","children":[]},{"id":"例","name":"例","children":[]},{"id":"parameters","name":"引数","children":[{"id":"parameters-factor","name":"factor","children":[]},{"id":"parameters-x","name":"x","children":[]},{"id":"parameters-y","name":"y","children":[]},{"id":"parameters-origin","name":"origin","children":[]},{"id":"parameters-reflow","name":"reflow","children":[]},{"id":"parameters-body","name":"body","children":[]}]}],"body":{"kind":"func","content":{"path":[],"name":"scale","title":"Scale","keywords":[],"oneliner":"レイアウトに影響を与えないコンテンツの拡大縮小。","element":true,"contextual":false,"deprecation":null,"details":"<p>レイアウトに影響を与えないコンテンツの拡大縮小。</p>\n<p>単一の軸で負のスケールを指定することで、コンテンツを反転表示できます。</p>\n<h2 id=\"例\">例</h2>\n<div class=\"previewed-code\"><pre><code><span class=\"typ-key\">#</span><span class=\"typ-key\">set</span> <span class=\"typ-func\">align</span><span class=\"typ-punct\">(</span>center<span class=\"typ-punct\">)</span>\n<span class=\"typ-func\">#</span><span class=\"typ-func\">scale</span><span class=\"typ-punct\">(</span>x<span class=\"typ-punct\">:</span> <span class=\"typ-op\">-</span><span class=\"typ-num\">100%</span><span class=\"typ-punct\">)</span><span class=\"typ-punct\">[</span>This is mirrored.<span class=\"typ-punct\">]</span>\n<span class=\"typ-func\">#</span><span class=\"typ-func\">scale</span><span class=\"typ-punct\">(</span>x<span class=\"typ-punct\">:</span> <span class=\"typ-op\">-</span><span class=\"typ-num\">100%</span><span class=\"typ-punct\">,</span> reflow<span class=\"typ-punct\">:</span> <span class=\"typ-key\">true</span><span class=\"typ-punct\">)</span><span class=\"typ-punct\">[</span>This is mirrored.<span class=\"typ-punct\">]</span>\n</code></pre><div class=\"preview\"><img src=\"/docs/assets/4a11fc3689aa86e118aeb7546c0a6368.png\" alt=\"Preview\"></div></div>","example":null,"self":false,"params":[{"name":"factor","details":"<p>位置引数として両方の軸の拡大縮小率を設定します。\nこれは<code>x</code>と<code>y</code>を同じ値で設定する省略記法です。</p>","example":null,"types":["auto","length","ratio"],"strings":[],"default":"<code><span class=\"typ-num\">100%</span></code>","positional":true,"named":false,"required":false,"variadic":false,"settable":true},{"name":"x","details":"<p>水平方向の拡大縮小率。</p>\n<p>負の値が指定された場合は本文が水平方向に反転します。</p>","example":null,"types":["auto","length","ratio"],"strings":[],"default":"<code><span class=\"typ-num\">100%</span></code>","positional":false,"named":true,"required":false,"variadic":false,"settable":true},{"name":"y","details":"<p>垂直方向の拡大縮小率。</p>\n<p>負の値が指定された場合は本文が垂直方向に反転します。</p>","example":null,"types":["auto","length","ratio"],"strings":[],"default":"<code><span class=\"typ-num\">100%</span></code>","positional":false,"named":true,"required":false,"variadic":false,"settable":true},{"name":"origin","details":"<p>変換の原点。</p>","example":"<div class=\"previewed-code\"><pre><code>A<span class=\"typ-func\">#</span><span class=\"typ-func\">box</span><span class=\"typ-punct\">(</span><span class=\"typ-func\">scale</span><span class=\"typ-punct\">(</span><span class=\"typ-num\">75%</span><span class=\"typ-punct\">)</span><span class=\"typ-punct\">[</span>A<span class=\"typ-punct\">]</span><span class=\"typ-punct\">)</span>A <span class=\"typ-escape\">\\</span>\nB<span class=\"typ-func\">#</span><span class=\"typ-func\">box</span><span class=\"typ-punct\">(</span><span class=\"typ-func\">scale</span><span class=\"typ-punct\">(</span><span class=\"typ-num\">75%</span><span class=\"typ-punct\">,</span> origin<span class=\"typ-punct\">:</span> bottom <span class=\"typ-op\">+</span> left<span class=\"typ-punct\">)</span><span class=\"typ-punct\">[</span>B<span class=\"typ-punct\">]</span><span class=\"typ-punct\">)</span>B\n</code></pre><div class=\"preview\"><img src=\"/docs/assets/753e3d1a1bca7e3f8a8ff37f29db41a9.png\" alt=\"Preview\"></div></div>","types":["alignment"],"strings":[],"default":"<code>center <span class=\"typ-op\">+</span> horizon</code>","positional":false,"named":true,"required":false,"variadic":false,"settable":true},{"name":"reflow","details":"<p>拡大縮小がレイアウトに影響を与えるかどうか。</p>\n<p><code><span class=\"typ-key\">false</span></code>の場合、拡大縮小したコンテンツが他のコンテンツと重なることを許可します。\n<code><span class=\"typ-key\">true</span></code>の場合、拡大縮小したコンテンツの新しい大きさを計算し、それに応じてレイアウトを調整します。</p>","example":"<div class=\"previewed-code\"><pre><code>Hello <span class=\"typ-func\">#</span><span class=\"typ-func\">scale</span><span class=\"typ-punct\">(</span>x<span class=\"typ-punct\">:</span> <span class=\"typ-num\">20%</span><span class=\"typ-punct\">,</span> y<span class=\"typ-punct\">:</span> <span class=\"typ-num\">40%</span><span class=\"typ-punct\">,</span> reflow<span class=\"typ-punct\">:</span> <span class=\"typ-key\">true</span><span class=\"typ-punct\">)</span><span class=\"typ-punct\">[</span>World<span class=\"typ-punct\">]</span>!\n</code></pre><div class=\"preview\"><img src=\"/docs/assets/f2a115827e2953ff282e69617b8717d9.png\" alt=\"Preview\"></div></div>","types":["bool"],"strings":[],"default":"<code><span class=\"typ-key\">false</span></code>","positional":false,"named":true,"required":false,"variadic":false,"settable":true},{"name":"body","details":"<p>拡大縮小するコンテンツ。</p>","example":null,"types":["content"],"strings":[],"default":null,"positional":true,"named":false,"required":true,"variadic":false,"settable":false}],"returns":["content"],"scope":[]}}}