{"route":"/docs/reference/math/attach/","title":"Attach","description":"Documentation for the attach functions.","part":null,"outline":[{"id":"summary","name":"概要","children":[]},{"id":"例","name":"例","children":[]},{"id":"構文","name":"構文","children":[]},{"id":"functions","name":"Functions","children":[{"id":"functions-attach","name":"Attach","children":[{"id":"functions-attach-base","name":"base","children":[]},{"id":"functions-attach-t","name":"t","children":[]},{"id":"functions-attach-b","name":"b","children":[]},{"id":"functions-attach-tl","name":"tl","children":[]},{"id":"functions-attach-bl","name":"bl","children":[]},{"id":"functions-attach-tr","name":"tr","children":[]},{"id":"functions-attach-br","name":"br","children":[]}]},{"id":"functions-scripts","name":"Scripts","children":[{"id":"functions-scripts-body","name":"body","children":[]}]},{"id":"functions-limits","name":"Limits","children":[{"id":"functions-limits-body","name":"body","children":[]},{"id":"functions-limits-inline","name":"inline","children":[]}]}]}],"body":{"kind":"group","content":{"name":"attach","title":"Attach","details":"<p>下付き文字、上付き文字、limits。</p>\n<p>アタッチメントは下付き文字、上付き文字、limitsのいずれかで表示することができます。\nTypstはベースに応じてどれがよりふさわしいかを自動的に決定しますが、<code>scripts</code>および<code>limits</code>関数を用いて手動で制御もできます。</p>\n<p>上部と下部の長いアタッチメント（例えば上部に文字がある矢印）に合うようにベースを伸縮させたい場合は<a href=\"/docs/reference/math/stretch/\"><code>stretch</code></a>関数を使用してください。</p>\n<h2 id=\"例\">例</h2>\n<div class=\"previewed-code\"><pre><code><span class=\"typ-math-delim\">$</span> <span class=\"typ-pol\">sum</span><span class=\"typ-math-op\">_</span><span class=\"typ-punct\">(</span>i=0<span class=\"typ-punct\">)</span><span class=\"typ-math-op\">^</span>n a<span class=\"typ-math-op\">_</span>i = 2<span class=\"typ-math-op\">^</span><span class=\"typ-punct\">(</span>1+i<span class=\"typ-punct\">)</span> <span class=\"typ-math-delim\">$</span>\n</code></pre><div class=\"preview\"><img src=\"/docs/assets/411437d70da7deb746bc3f0a67ecac51.png\" alt=\"Preview\"></div></div>\n<h2 id=\"構文\">構文</h2>\n<p>この関数にはベースの後ろのアタッチメントのための専用の構文があります。\n下付き文字、すなわち下部のアタッチメントにはアンダースコア（<code>_</code>）を、上付き文字、すなわち上部のアタッチメントにはサーカムフレックス（<code>^</code>）を使用してください。</p>","functions":[{"path":["math"],"name":"attach","title":"Attach","keywords":[],"oneliner":"オプションのアタッチメントを持つベースとなる関数。","element":true,"contextual":false,"deprecation":null,"details":"<p>オプションのアタッチメントを持つベースとなる関数。</p>","example":"<div class=\"previewed-code\"><pre><code><span class=\"typ-math-delim\">$</span> <span class=\"typ-func\">attach</span><span class=\"typ-punct\">(</span>\n  <span class=\"typ-pol\">Pi</span><span class=\"typ-punct\">,</span> t<span class=\"typ-punct\">:</span> <span class=\"typ-pol\">alpha</span><span class=\"typ-punct\">,</span> b<span class=\"typ-punct\">:</span> <span class=\"typ-pol\">beta</span><span class=\"typ-punct\">,</span>\n  tl<span class=\"typ-punct\">:</span> 1<span class=\"typ-punct\">,</span> tr<span class=\"typ-punct\">:</span> 2+3<span class=\"typ-punct\">,</span> bl<span class=\"typ-punct\">:</span> 4+5<span class=\"typ-punct\">,</span> br<span class=\"typ-punct\">:</span> 6<span class=\"typ-punct\">,</span>\n<span class=\"typ-punct\">)</span> <span class=\"typ-math-delim\">$</span>\n</code></pre><div class=\"preview\"><img src=\"/docs/assets/84fd52f8518c49b5d0c2154d3762e8c5.png\" alt=\"Preview\"></div></div>","self":false,"params":[{"name":"base","details":"<p>アタッチメントを取り付けるベース。</p>","example":null,"types":["content"],"strings":[],"default":null,"positional":true,"named":false,"required":true,"variadic":false,"settable":false},{"name":"t","details":"<p>右上かベースの上にスマート配置された上部アタッチメント。</p>\n<p>ベースを<code><span class=\"typ-func\">limits</span><span class=\"typ-punct\">(</span><span class=\"typ-punct\">)</span></code>か<code><span class=\"typ-func\">scripts</span><span class=\"typ-punct\">(</span><span class=\"typ-punct\">)</span></code>でラップするとスマート配置を上書きできます。</p>","example":null,"types":["none","content"],"strings":[],"default":"<code><span class=\"typ-key\">none</span></code>","positional":false,"named":true,"required":false,"variadic":false,"settable":true},{"name":"b","details":"<p>右下かベースの下にスマート配置された下部アタッチメント。</p>\n<p>ベースを<code><span class=\"typ-func\">limits</span><span class=\"typ-punct\">(</span><span class=\"typ-punct\">)</span></code>か<code><span class=\"typ-func\">scripts</span><span class=\"typ-punct\">(</span><span class=\"typ-punct\">)</span></code>でラップするとスマート配置を上書きできます。</p>","example":null,"types":["none","content"],"strings":[],"default":"<code><span class=\"typ-key\">none</span></code>","positional":false,"named":true,"required":false,"variadic":false,"settable":true},{"name":"tl","details":"<p>左上のアタッチメント（ベースの前）。</p>","example":null,"types":["none","content"],"strings":[],"default":"<code><span class=\"typ-key\">none</span></code>","positional":false,"named":true,"required":false,"variadic":false,"settable":true},{"name":"bl","details":"<p>左下のアタッチメント（ベースの前）。</p>","example":null,"types":["none","content"],"strings":[],"default":"<code><span class=\"typ-key\">none</span></code>","positional":false,"named":true,"required":false,"variadic":false,"settable":true},{"name":"tr","details":"<p>右上のアタッチメント（ベースの後）。</p>","example":null,"types":["none","content"],"strings":[],"default":"<code><span class=\"typ-key\">none</span></code>","positional":false,"named":true,"required":false,"variadic":false,"settable":true},{"name":"br","details":"<p>右下のアタッチメント（ベースの後）。</p>","example":null,"types":["none","content"],"strings":[],"default":"<code><span class=\"typ-key\">none</span></code>","positional":false,"named":true,"required":false,"variadic":false,"settable":true}],"returns":["content"],"scope":[]},{"path":["math"],"name":"scripts","title":"Scripts","keywords":[],"oneliner":"アタッチメントを添え字として表示することをベースに強制。","element":true,"contextual":false,"deprecation":null,"details":"<p>アタッチメントを添え字として表示することをベースに強制。</p>","example":"<div class=\"previewed-code\"><pre><code><span class=\"typ-math-delim\">$</span> <span class=\"typ-func\">scripts</span><span class=\"typ-punct\">(</span><span class=\"typ-pol\">sum</span><span class=\"typ-punct\">)</span><span class=\"typ-math-op\">_</span>1<span class=\"typ-math-op\">^</span>2 <span class=\"typ-escape\">!=</span> <span class=\"typ-pol\">sum</span><span class=\"typ-math-op\">_</span>1<span class=\"typ-math-op\">^</span>2 <span class=\"typ-math-delim\">$</span>\n</code></pre><div class=\"preview\"><img src=\"/docs/assets/c9599c27cd86c13285b8d314e2c8528c.png\" alt=\"Preview\"></div></div>","self":false,"params":[{"name":"body","details":"<p>添え字を取り付けるベース。</p>","example":null,"types":["content"],"strings":[],"default":null,"positional":true,"named":false,"required":true,"variadic":false,"settable":false}],"returns":["content"],"scope":[]},{"path":["math"],"name":"limits","title":"Limits","keywords":[],"oneliner":"アタッチメントをlimitsとして表示することをベースに強制。","element":true,"contextual":false,"deprecation":null,"details":"<p>アタッチメントをlimitsとして表示することをベースに強制。</p>","example":"<div class=\"previewed-code\"><pre><code><span class=\"typ-math-delim\">$</span> <span class=\"typ-func\">limits</span><span class=\"typ-punct\">(</span>A<span class=\"typ-punct\">)</span><span class=\"typ-math-op\">_</span>1<span class=\"typ-math-op\">^</span>2 <span class=\"typ-escape\">!=</span> A<span class=\"typ-math-op\">_</span>1<span class=\"typ-math-op\">^</span>2 <span class=\"typ-math-delim\">$</span>\n</code></pre><div class=\"preview\"><img src=\"/docs/assets/ffb91cddf4edf78f1af94d7ff70772ce.png\" alt=\"Preview\"></div></div>","self":false,"params":[{"name":"body","details":"<p>limitsを取り付けるベース。</p>","example":null,"types":["content"],"strings":[],"default":null,"positional":true,"named":false,"required":true,"variadic":false,"settable":false},{"name":"inline","details":"<p>インライン数式でもlimits表示を強制するかどうか。</p>\n<p>（例えばshowルールを用いて）limitsをグローバルに適用する場合、通常は無効にすることをおすすめします。</p>","example":null,"types":["bool"],"strings":[],"default":"<code><span class=\"typ-key\">true</span></code>","positional":false,"named":true,"required":false,"variadic":false,"settable":true}],"returns":["content"],"scope":[]}]}}}