{"route":"/docs/reference/layout/align/","title":"Align","description":"Documentation for the `align` function.","part":null,"outline":[{"id":"summary","name":"概要","children":[]},{"id":"例","name":"例","children":[]},{"id":"配置の組み合わせ","name":"配置の組み合わせ","children":[]},{"id":"配置のネスト","name":"配置のネスト","children":[]},{"id":"同一行での配置設定","name":"同一行での配置設定","children":[]},{"id":"parameters","name":"引数","children":[{"id":"parameters-alignment","name":"alignment","children":[]},{"id":"parameters-body","name":"body","children":[]}]}],"body":{"kind":"func","content":{"path":[],"name":"align","title":"Align","keywords":[],"oneliner":"コンテンツを水平方向・垂直方向に配置。","element":true,"contextual":false,"deprecation":null,"details":"<p>コンテンツを水平方向・垂直方向に配置。</p>\n<h2 id=\"例\">例</h2>\n<p>コンテンツを水平方向に中央揃えにすることから始めましょう。</p>\n<div class=\"previewed-code\"><pre><code><span class=\"typ-key\">#</span><span class=\"typ-key\">set</span> <span class=\"typ-func\">page</span><span class=\"typ-punct\">(</span>height<span class=\"typ-punct\">:</span> <span class=\"typ-num\">120pt</span><span class=\"typ-punct\">)</span>\n<span class=\"typ-key\">#</span><span class=\"typ-key\">set</span> <span class=\"typ-func\">align</span><span class=\"typ-punct\">(</span>center<span class=\"typ-punct\">)</span>\n\nCentered text, a sight to see <span class=\"typ-escape\">\\</span>\nIn perfect balance, visually <span class=\"typ-escape\">\\</span>\nNot left nor right, it stands alone <span class=\"typ-escape\">\\</span>\nA work of art, a visual throne\n</code></pre><div class=\"preview\"><img src=\"/docs/assets/91c3481be6d803c4fd0540e78c25091a.png\" alt=\"Preview\"></div></div>\n<p>垂直方向に中央揃えにするには <em>horizon</em> 配置を使用します。</p>\n<div class=\"previewed-code\"><pre><code><span class=\"typ-key\">#</span><span class=\"typ-key\">set</span> <span class=\"typ-func\">page</span><span class=\"typ-punct\">(</span>height<span class=\"typ-punct\">:</span> <span class=\"typ-num\">120pt</span><span class=\"typ-punct\">)</span>\n<span class=\"typ-key\">#</span><span class=\"typ-key\">set</span> <span class=\"typ-func\">align</span><span class=\"typ-punct\">(</span>horizon<span class=\"typ-punct\">)</span>\n\nVertically centered, <span class=\"typ-escape\">\\</span>\nthe stage had entered, <span class=\"typ-escape\">\\</span>\na new paragraph.\n</code></pre><div class=\"preview\"><img src=\"/docs/assets/cbd38ef8c4834081d6b063dcffaa4d9c.png\" alt=\"Preview\"></div></div>\n<h2 id=\"配置の組み合わせ\">配置の組み合わせ</h2>\n<p><code>+</code>演算子を用いて2種類の配置を組み合わせることができます。\nsetルールの代わりに関数形式を用いて1つのコンテンツのみに適用してみましょう。</p>\n<div class=\"previewed-code\"><pre><code><span class=\"typ-key\">#</span><span class=\"typ-key\">set</span> <span class=\"typ-func\">page</span><span class=\"typ-punct\">(</span>height<span class=\"typ-punct\">:</span> <span class=\"typ-num\">120pt</span><span class=\"typ-punct\">)</span>\nThough left in the beginning <span class=\"typ-escape\">...</span>\n\n<span class=\"typ-func\">#</span><span class=\"typ-func\">align</span><span class=\"typ-punct\">(</span>right <span class=\"typ-op\">+</span> bottom<span class=\"typ-punct\">)</span><span class=\"typ-punct\">[</span>\n  <span class=\"typ-escape\">...</span> they were right in the end, <span class=\"typ-escape\">\\</span>\n  and with addition had gotten, <span class=\"typ-escape\">\\</span>\n  the paragraph to the bottom!\n<span class=\"typ-punct\">]</span>\n</code></pre><div class=\"preview\"><img src=\"/docs/assets/8176aa00c602f0b89c8ff5022b425216.png\" alt=\"Preview\"></div></div>\n<h2 id=\"配置のネスト\">配置のネスト</h2>\n<p>レイアウトコンテナおよびその内部の要素にさまざまな配置設定を適用できます。\nこのようにすることで複雑なレイアウトを作成できます。</p>\n<div class=\"previewed-code\"><pre><code><span class=\"typ-func\">#</span><span class=\"typ-func\">align</span><span class=\"typ-punct\">(</span>center<span class=\"typ-punct\">,</span> <span class=\"typ-func\">block</span><span class=\"typ-punct\">[</span>\n  <span class=\"typ-key\">#</span><span class=\"typ-key\">set</span> <span class=\"typ-func\">align</span><span class=\"typ-punct\">(</span>left<span class=\"typ-punct\">)</span>\n  Though centered together <span class=\"typ-escape\">\\</span>\n  alone <span class=\"typ-escape\">\\</span>\n  we <span class=\"typ-escape\">\\</span>\n  are <span class=\"typ-escape\">\\</span>\n  left.\n<span class=\"typ-punct\">]</span><span class=\"typ-punct\">)</span>\n</code></pre><div class=\"preview\"><img src=\"/docs/assets/7a63e59616d8948c21cd27d07c47cbd.png\" alt=\"Preview\"></div></div>\n<h2 id=\"同一行での配置設定\">同一行での配置設定</h2>\n<p><code>align</code> 関数はブロックレベルで配置を実行するため、常に現在のパラグラフを中断します。\n同じ行の一部を異なる配置にするためには、代わりに<a href=\"/docs/reference/layout/h/\">比率間隔</a>を使用しなければなりません。</p>\n<div class=\"previewed-code\"><pre><code>Start <span class=\"typ-func\">#</span><span class=\"typ-func\">h</span><span class=\"typ-punct\">(</span><span class=\"typ-num\">1fr</span><span class=\"typ-punct\">)</span> End\n</code></pre><div class=\"preview\"><img src=\"/docs/assets/8e569fc1b13666e212c093d0351cc0de.png\" alt=\"Preview\"></div></div>","example":null,"self":false,"params":[{"name":"alignment","details":"<p>両方の軸に沿った<a href=\"/docs/reference/layout/alignment/\" title=\"alignment\">alignment</a>。</p>","example":"<div class=\"previewed-code\"><pre><code><span class=\"typ-key\">#</span><span class=\"typ-key\">set</span> <span class=\"typ-func\">page</span><span class=\"typ-punct\">(</span>height<span class=\"typ-punct\">:</span> <span class=\"typ-num\">6cm</span><span class=\"typ-punct\">)</span>\n<span class=\"typ-key\">#</span><span class=\"typ-key\">set</span> <span class=\"typ-func\">text</span><span class=\"typ-punct\">(</span>lang<span class=\"typ-punct\">:</span> <span class=\"typ-str\">&quot;ar&quot;</span><span class=\"typ-punct\">)</span>\n\nمثال\n<span class=\"typ-func\">#</span><span class=\"typ-func\">align</span><span class=\"typ-punct\">(</span>\n  end <span class=\"typ-op\">+</span> horizon<span class=\"typ-punct\">,</span>\n  <span class=\"typ-func\">rect</span><span class=\"typ-punct\">(</span>inset<span class=\"typ-punct\">:</span> <span class=\"typ-num\">12pt</span><span class=\"typ-punct\">)</span><span class=\"typ-punct\">[</span>ركن<span class=\"typ-punct\">]</span>\n<span class=\"typ-punct\">)</span>\n</code></pre><div class=\"preview\"><img src=\"/docs/assets/df5efabe6e8813f04d7d9ad5a5cf7fc4.png\" alt=\"Preview\"></div></div>","types":["alignment"],"strings":[],"default":"<code>start <span class=\"typ-op\">+</span> top</code>","positional":true,"named":false,"required":false,"variadic":false,"settable":true},{"name":"body","details":"<p>配置するコンテンツ。</p>","example":null,"types":["content"],"strings":[],"default":null,"positional":true,"named":false,"required":true,"variadic":false,"settable":false}],"returns":["content"],"scope":[]}}}